beritapopuler/__init__.py
latestrendingnews_indonesia-0.4.1.dist-info/LICENSE
latestrendingnews_indonesia-0.4.1.dist-info/METADATA
latestrendingnews_indonesia-0.4.1.dist-info/WHEEL
latestrendingnews_indonesia-0.4.1.dist-info/top_level.txt
latestrendingnews_indonesia-0.4.1.dist-info/RECORD
