Metadata-Version: 2.1
Name: latestrendingnews-indonesia
Version: 0.4.1
Summary: This package will display the latest trending news data taken from detik.com
Home-page: https://github.com/Reinz-Stuff/latest-trending-news
Author: Fauzi Kurniawan
Author-email: fauzik354313@gmail.com
Project-URL: Github, https://github.com/Reinz-Stuff
Classifier: Programming Language :: Python :: 3
Classifier: License :: OSI Approved :: GNU General Public License v3 (GPLv3)
Classifier: Operating System :: OS Independent
Classifier: Development Status :: 4 - Beta
Requires-Python: >=3.6
License-File: LICENSE
